rapidgator_api/__init__.py
rapidgator_api/client.py
rapidgator_api/exceptions.py
rapidgator_api/models.py
rapidgator_api-1.1.0.dist-info/METADATA
rapidgator_api-1.1.0.dist-info/WHEEL
rapidgator_api-1.1.0.dist-info/top_level.txt
rapidgator_api-1.1.0.dist-info/RECORD
