Metadata-Version: 2.1
Name: rapidgator-api
Version: 1.1.0
Summary: Python client library for the Rapidgator API
Home-page: https://git.goocat.gay
Author: Zack3D
Author-email: zack3d@goocat.gay
License: UNKNOWN
Platform: UNKNOWN
Classifier: Programming Language :: Python :: 3
Requires-Dist: requests
Requires-Dist: tqdm
